HISTORY.rst
LICENSE
MANIFEST.in
README.rst
setup.cfg
setup.py
salesforce_bulk/__init__.py
salesforce_bulk/bulk_states.py
salesforce_bulk/csv_adapter.py
salesforce_bulk/salesforce_bulk.py
salesforce_bulk_yplan.egg-info/PKG-INFO
salesforce_bulk_yplan.egg-info/SOURCES.txt
salesforce_bulk_yplan.egg-info/dependency_links.txt
salesforce_bulk_yplan.egg-info/not-zip-safe
salesforce_bulk_yplan.egg-info/requires.txt
salesforce_bulk_yplan.egg-info/top_level.txt
tests/__init__.py
tests/test_salesforce_bulk.py
tests/test_salesforce_bulk2.py