Metadata-Version: 1.1
Name: salesforce-bulk-yplan
Version: 1.2.0
Summary: Python interface to the Salesforce.com Bulk API.
Home-page: https://github.com/YPlan/salesforce-bulk
Author: YPlan
Author-email: julius@yplanapp.com
License: Copyright (c) 2013 Scott Persinger
